finder/__init__.py
finder/finder.py
agent_finder_masterjefferson-1.0.dist-info/LICENSE
agent_finder_masterjefferson-1.0.dist-info/METADATA
agent_finder_masterjefferson-1.0.dist-info/WHEEL
agent_finder_masterjefferson-1.0.dist-info/entry_points.txt
agent_finder_masterjefferson-1.0.dist-info/top_level.txt
agent_finder_masterjefferson-1.0.dist-info/RECORD
