Metadata-Version: 2.1
Name: agent-finder-masterjefferson
Version: 1.0
Summary: Find nearby auto insurance agents and dump them to a CSV file.
Home-page: https://github.com/masterjefferson/agent-finder
Author: Jefferson Jones
Author-email: jeffersonmjones92@gmail.com
License: UNKNOWN
Platform: UNKNOWN
Classifier: Programming Language :: Python :: 3
Classifier: License :: OSI Approved :: MIT License
Classifier: Operating System :: MacOS
Requires-Python: >=3.7.5
Requires-Dist: googlemaps
